[
    {
        "id": "13171085",
        "question": "Hạn nộp: 09:35 23/03/2026\nNguyên tố nhóm IA (Nâng cao)\n Nộp Bài\nPhiếu trả lời\nSố câu đã làm:\n24\nSố câu chưa làm:\n4\nPHẦN I. Trắc nghiệm nhiều phương án lựa chọn\n1\n2\n3\n4\n5\n6\n7\n8\n9\n10\n11\n12\n13\n14\n15\n16\n17\n18\nPHẦN III. Trắc nghiệm trả lời ngắn\n19\n20\n21\n22\n23\n24\nPHẦN II. Trắc nghiệm đúng sai\n25\n26\n27\n28\nChưa làm\nĐã làm\nCâu: 25 #13171085\n Báo lỗi\nTrong mỗi ý ở câu dưới đây, hãy chọn đúng hoặc sai.\n\nNhiệt tạo thành của một số chất được cho trong bảng sau:\n\n\n\na)\nQuá trình hình thành muối NaHCO3 từ các đơn chất thuận lợi về năng lượng hơn so với quá trình hình thành muối Na2CO3 từ các đơn chất.\nĐúng\nSai\nb)\nGiá trị biến thiên enthalpy chuẩn của phản ứng 2NaHCO3(s) → Na2CO3(s) + H2O(l) + CO2(g) là −91,28kJ.\nĐúng\nSai\nc)\nPhản ứng Na2CO3(s) → Na2O(s) + CO2(g) không diễn ra ở điều kiện thường, phù hợp với giá trị biến thiên enthalpy chuẩn của phản ứng khá dương.\nĐúng\nSai\nd)\nNa2CO3 bền với nhiệt hơn NaHCO3.\nĐúng\nSai\nBỎ QUA",
        "answers": {
            "a": "Sai",
            "b": "Sai",
            "c": "Đúng",
            "d": "Đúng"
        }
    },
    {
        "id": "13171088",
        "question": "Hạn nộp: 09:35 23/03/2026\nNguyên tố nhóm IA (Nâng cao)\n Nộp Bài\nPhiếu trả lời\nSố câu đã làm:\n25\nSố câu chưa làm:\n3\nPHẦN I. Trắc nghiệm nhiều phương án lựa chọn\n1\n2\n3\n4\n5\n6\n7\n8\n9\n10\n11\n12\n13\n14\n15\n16\n17\n18\nPHẦN III. Trắc nghiệm trả lời ngắn\n19\n20\n21\n22\n23\n24\nPHẦN II. Trắc nghiệm đúng sai\n25\n26\n27\n28\nChưa làm\nĐã làm\nCâu: 26 #13171088\n Báo lỗi\nTrong mỗi ý ở câu dưới đây, hãy chọn đúng hoặc sai.\n\nDùng panh lấy các mẫu kim loại (Li, Na hoặc K) có kích cỡ xấp xỉ nhau đã thấm khô dầu và cho vào các chậu thuỷ tinh đã chứa khoảng 1/3 thể tích nước. Thêm 2 – 3 giọt dung dịch phenolphthalein vào chậu sau khi kim loại tan hết.\n\na)\nCác dung dịch thu được sau phản ứng đều có màu hồng.\nĐúng\nSai\nb)\nTrong nước, potassium tan nhanh hơn so với sodium, sodium tan nhanh hơn so với lithium.\nĐúng\nSai\nc)\nCác cặp oxi hoá – khử M+/M (M: Li, Na, K) đều có giá trị thế điện cực chuẩn lớn hơn giá trị thế điện cực chuẩn của cặp oxi hoá – khử 2H2O/H2 + 2OH–.\nĐúng\nSai\nd)\nKết quả thí nghiệm cho kết luận tính khử của các kim loại tăng dần theo dãy K, Na, Li.\nĐúng\nSai\nBỎ QUA",
        "answers": {
            "a": "Đúng",
            "b": "Đúng",
            "c": "Sai",
            "d": "Sai"
        }
    },
    {
        "id": "13171093",
        "question": "Hạn nộp: 09:35 23/03/2026\nNguyên tố nhóm IA (Nâng cao)\n Nộp Bài\nPhiếu trả lời\nSố câu đã làm:\n26\nSố câu chưa làm:\n2\nPHẦN I. Trắc nghiệm nhiều phương án lựa chọn\n1\n2\n3\n4\n5\n6\n7\n8\n9\n10\n11\n12\n13\n14\n15\n16\n17\n18\nPHẦN III. Trắc nghiệm trả lời ngắn\n19\n20\n21\n22\n23\n24\nPHẦN II. Trắc nghiệm đúng sai\n25\n26\n27\n28\nChưa làm\nĐã làm\nCâu: 27 #13171093\n Báo lỗi\nTrong mỗi ý ở câu dưới đây, hãy chọn đúng hoặc sai.\n\nSodium sulfate (Na2SO4) được ứng dụng trong sản xuất giấy, thuỷ tinh, chất tẩy rửa. Trong công nghiệp, Na2SO4 được sản xuất bằng cách đun H2SO4 với NaCl. Người ta dùng một lượng H2SO4 vừa đủ, nồng độ 75% đun với NaCl. Sau phản ứng thu được sản phẩm có tỉ lệ về khối lượng như sau: 91,48% Na2SO4; 4,79% NaHSO4; 1,98% NaCl; 1,35% H2O; 0,40% HCl.\nCho các phản ứng hoá học xảy ra:\n(1) H2SO4(aq) + 2NaCl(s) → Na2SO4(s) + 2HCl(g)\n(2) H2SO4(aq) + NaCl(s) → NaHSO4(s) + HCl(g)\n\na)\nChất rắn thu được sau phản ứng gồm có 2 chất là Na2SO4 và NaHSO4.\nĐúng\nSai\nb)\nTỉ lệ % NaCl đã chuyển hoá thành Na2SO4 là 97,5%.\nĐúng\nSai\nc)\nNếu dùng 1 tấn NaCl sẽ tạo ra 1,148 tấn Na2SO4.\nĐúng\nSai\nd)\nTỉ lệ NaCl đã tham gia phản ứng là 95,7%.\nĐúng\nSai\nBỎ QUA",
        "answers": {
            "a": "Sai",
            "b": "Sai",
            "c": "Đúng",
            "d": "Sai"
        }
    },
    {
        "id": "13171096",
        "question": "Hạn nộp: 09:35 23/03/2026\nNguyên tố nhóm IA (Nâng cao)\n Nộp Bài\nPhiếu trả lời\nSố câu đã làm:\n27\nSố câu chưa làm:\n1\nPHẦN I. Trắc nghiệm nhiều phương án lựa chọn\n1\n2\n3\n4\n5\n6\n7\n8\n9\n10\n11\n12\n13\n14\n15\n16\n17\n18\nPHẦN III. Trắc nghiệm trả lời ngắn\n19\n20\n21\n22\n23\n24\nPHẦN II. Trắc nghiệm đúng sai\n25\n26\n27\n28\nChưa làm\nĐã làm\nCâu: 28 #13171096\n Báo lỗi\nTrong mỗi ý ở câu dưới đây, hãy chọn đúng hoặc sai.\n\nCho đồ thị về độ tan của một số chất rắn trong nước: NaNO3, KBr, KNO3, NaCl, Na2SO4 trong hình vẽ sau:\na)\nĐộ tan của các chất rắn đều tăng khi nhiệt độ tăng.\nĐúng\nSai\nb)\nTrong các chất trên, chất có độ tan phụ thuộc nhiều nhất và ít nhất vào nhiệt độ là KNO3 và Na2SO4.\nĐúng\nSai\nc)\nChất có độ tan lớn nhất ở 60 oC là NaNO3.\nĐúng\nSai\nd)\nChất có độ tan nhỏ nhất ở 20 oC là NaCl.\nĐúng\nSai\nBỎ QUA",
        "answers": {
            "a": "Sai",
            "b": "Sai",
            "c": "Đúng",
            "d": "Sai"
        }
    },
    {
        "id": "13171095",
        "question": "Hạn nộp: 09:35 23/03/2026\nNguyên tố nhóm IA (Cơ bản)\n Nộp Bài\nPhiếu trả lời\nSố câu đã làm:\n0\nSố câu chưa làm:\n28\nPHẦN II. Trắc nghiệm đúng sai\n1\n2\n3\n4\nPHẦN I. Trắc nghiệm nhiều phương án lựa chọn\n5\n6\n7\n8\n9\n10\n11\n12\n13\n14\n15\n16\n17\n18\n19\n20\n21\n22\nPHẦN III. Trắc nghiệm trả lời ngắn\n23\n24\n25\n26\n27\n28\nChưa làm\nĐã làm\nCâu: 1 #13171095\n Báo lỗi\nTrong mỗi ý ở câu dưới đây, hãy chọn đúng hoặc sai.\n\nCho giá trị độ tan trong nước ở 298 K của một số chất trong bảng sau:\n \nChất\tLi2CO3\tLiI\tNa2CO3\tNaOH\tCs2CO3\tKNO3\nĐộ tan (g/100 g H2O)\t1,33\t165\t21,5\t109\t234\t31,6\na)\nChất tan kém nhất trong nước ở 298 K là Li2CO3.\nĐúng\nSai\nb)\nDung dịch Na2CO3 bão hoà ở 298 K có nồng độ phần trăm là khoảng 17,7%.\nĐúng\nSai\nc)\nKhối lượng NaOH trong 200 g dung dịch NaOH bão hoà ở 298 K là 218 g.\nĐúng\nSai\nd)\nĐể hoà tan hết 94,8 g KNO3 ở 298 K cần tối thiểu 300 g nước.\nĐúng\nSai\nBỎ QUA",
        "answers": {
            "a": "Đúng",
            "b": "Đúng",
            "c": "Sai",
            "d": "Đúng"
        }
    },
    {
        "id": "13171098",
        "question": "Hạn nộp: 09:35 23/03/2026\nNguyên tố nhóm IA (Cơ bản)\n Nộp Bài\nPhiếu trả lời\nSố câu đã làm:\n1\nSố câu chưa làm:\n27\nPHẦN II. Trắc nghiệm đúng sai\n1\n2\n3\n4\nPHẦN I. Trắc nghiệm nhiều phương án lựa chọn\n5\n6\n7\n8\n9\n10\n11\n12\n13\n14\n15\n16\n17\n18\n19\n20\n21\n22\nPHẦN III. Trắc nghiệm trả lời ngắn\n23\n24\n25\n26\n27\n28\nChưa làm\nĐã làm\nCâu: 2 #13171098\n Báo lỗi\nTrong mỗi ý ở câu dưới đây, hãy chọn đúng hoặc sai.\n\nTrong công nghiệp, chất X và Y được sản xuất theo các giai đoạn sau:\n- Giai đoạn 1: Hoà tan NaCl vào dung dịch NH3 đặc đến bão hoà.\nNung CaCO3 rồi dẫn khí thoát ra vào dung dịch bão hoà của NaCl trong NH3.\n- Giai đoạn 2: Sau một thời gian, làm lạnh dung dịch, chất X tách ra khỏi dung dịch, nung chất X ở nhiệt độ cao thu được chất Y.\n\na)\nChất X và Y lần lượt là NaHCO3 và Na2CO3.\nĐúng\nSai\nb)\nPhương pháp sản xuất chất X, Y trên được gọi là phương pháp Solvay.\nĐúng\nSai\nc)\nĐể tái sử dụng NaCl có thể cho dung dịch sau giai đoạn 2 phản ứng với Ca(OH)2.\nĐúng\nSai\nd)\nPhản ứng của khí CO2 với NaCl trong NH3 là phản ứng một chiều.\nĐúng\nSai\nBỎ QUA",
        "answers": {
            "a": "Đúng",
            "b": "Đúng",
            "c": "Sai",
            "d": "Sai"
        }
    },
    {
        "id": "13171100",
        "question": "Hạn nộp: 09:35 23/03/2026\nNguyên tố nhóm IA (Cơ bản)\n Nộp Bài\nPhiếu trả lời\nSố câu đã làm:\n2\nSố câu chưa làm:\n26\nPHẦN II. Trắc nghiệm đúng sai\n1\n2\n3\n4\nPHẦN I. Trắc nghiệm nhiều phương án lựa chọn\n5\n6\n7\n8\n9\n10\n11\n12\n13\n14\n15\n16\n17\n18\n19\n20\n21\n22\nPHẦN III. Trắc nghiệm trả lời ngắn\n23\n24\n25\n26\n27\n28\nChưa làm\nĐã làm\nCâu: 3 #13171100\n Báo lỗi\nTrong mỗi ý ở câu dưới đây, hãy chọn đúng hoặc sai.\n\nTrong công nghiệp chlorine – kiềm, quá trình điện phân dung dịch NaCl bão hoà có màng ngăn điện cực được ứng dụng để sản xuất xút công nghiệp (NaOH) và khí chlorine (Cl2). Cho sơ đồ quá trình điện phân dung dịch NaCl bão hoà trong công nghiệp:\na)\nMàng ngăn điện cực để ngăn không cho Cl2 tiếp xúc với OH-.\nĐúng\nSai\nb)\n\nỞ anode xảy ra quá trình khử: 2H2O + 2e → H2 + 2OH-.\n\nĐúng\nSai\nc)\nPhương trình điện phân: 2NaCl + 2H2O \n→\n𝑐\n𝑜\n𝑚\n𝑎\n𝑛\n𝑔\n𝑛\n𝑔\n𝑎\n𝑛\n𝑑\n𝑝\n𝑑\n𝑑\n 2NaOH + Cl2 + H2.\nĐúng\nSai\nd)\nDung dịch thu được sau điện phân có thành phần chính NaOH và còn lẫn NaCl.\nĐúng\nSai\nBỎ QUA",
        "answers": {
            "a": "Đúng",
            "b": "Sai",
            "c": "Đúng",
            "d": "Đúng"
        }
    },
    {
        "id": "13171101",
        "question": "Hạn nộp: 09:35 23/03/2026\nNguyên tố nhóm IA (Cơ bản)\n Nộp Bài\nPhiếu trả lời\nSố câu đã làm:\n3\nSố câu chưa làm:\n25\nPHẦN II. Trắc nghiệm đúng sai\n1\n2\n3\n4\nPHẦN I. Trắc nghiệm nhiều phương án lựa chọn\n5\n6\n7\n8\n9\n10\n11\n12\n13\n14\n15\n16\n17\n18\n19\n20\n21\n22\nPHẦN III. Trắc nghiệm trả lời ngắn\n23\n24\n25\n26\n27\n28\nChưa làm\nĐã làm\nCâu: 4 #13171101\n Báo lỗi\nTrong mỗi ý ở câu dưới đây, hãy chọn đúng hoặc sai.\n\nKim loại kiềm và các hợp chất của kim loại kiềm có nhiều ứng dụng trong thực tế.\n\na)\nSodium được dùng để loại nước khỏi một số dung môi hữu cơ (như ether).\nĐúng\nSai\nb)\nCó thể sử dụng ethanol để bảo quản kim loại Na hoặc K.\nĐúng\nSai\nc)\nCó thể dụng Na2CO3 để rửa bồn rửa bát có lớp dầu mỡ bám vào.\nĐúng\nSai\nd)\nSodium hydrogencarbonate dùng để tăng độ xốp của bánh, làm mềm thực phẩm.\nĐúng\nSai\nBỎ QUA",
        "answers": {
            "a": "Đúng",
            "b": "Sai",
            "c": "Đúng",
            "d": "Đúng"
        }
    }
]